CHANGELOG.md
LICENSE.txt
django_sb_codefield/__init__.py
django_sb_codefield/admin.py
django_sb_codefield/apps.py
django_sb_codefield/fields.py
django_sb_codefield/models.py
django_sb_codefield/static/django_sb_codefield/css/codefield_django_admin.css
django_sb_codefield/tests.py
django_sb_codefield/version.py
django_sb_codefield/views.py
django_sb_codefield-0.4.0.dist-info/LICENSE.txt
django_sb_codefield-0.4.0.dist-info/METADATA
django_sb_codefield-0.4.0.dist-info/WHEEL
django_sb_codefield-0.4.0.dist-info/RECORD
