Metadata-Version: 2.1
Name: django-sb-codefield
Version: 0.4.0
Summary: Use codemirror2 widget directly in Django models, forms and admin.
Home-page: https://gitlab.com/softbutterfly/open-source/django-sb-codefield
License: MIT
Keywords: Softbutterfly,Django,Migrations
Author: SoftButterfly Development Team
Author-email: dev@softbutterfly.io
Requires-Python: >=3.10.0,<4.0.0
Classifier: Development Status :: 5 - Production/Stable
Classifier: Environment :: Web Environment
Classifier: Framework :: Django :: 4.2
Classifier: Framework :: Django :: 5.0
Classifier: Framework :: Django :: 5.1
Classifier: Intended Audience :: Developers
Classifier: License :: OSI Approved :: MIT License
Classifier: Natural Language :: English
Classifier: Programming Language :: Python :: 3
Classifier: Programming Language :: Python :: 3.10
Classifier: Programming Language :: Python :: 3.11
Classifier: Programming Language :: Python :: 3.12
Classifier: Programming Language :: Python :: 3.8
Classifier: Programming Language :: Python :: 3.9
Classifier: Topic :: Software Development :: Libraries :: Python Modules
Requires-Dist: django (>=5.1,<6.0)
Requires-Dist: django-codemirror2 (>=0.2,<0.3)
Project-URL: Bug Tracker, https://gitlab.com/softbutterfly/open-source/django-sb-codefield/-/issues
Project-URL: Documentation, https://gitlab.com/softbutterfly/open-source/django-sb-codefield/-/wikis
Project-URL: Download, https://gitlab.com/softbutterfly/open-source/django-sb-codefield/-/archive/v0.4.0/django-sb-codefield-v0.4.0.tar.gz
Project-URL: Repository, https://gitlab.com/softbutterfly/open-source/django-sb-codefield
